ijcache/__init__.py
ijcache-0.0.1.dist-info/LICENSE
ijcache-0.0.1.dist-info/METADATA
ijcache-0.0.1.dist-info/WHEEL
ijcache-0.0.1.dist-info/top_level.txt
ijcache-0.0.1.dist-info/RECORD
