Metadata-Version: 2.1
Name: ijcache
Version: 0.0.1
Summary: A fast Cache module written in Python
Home-page: https://github.com/urain39/ijcache
Author: urain39
Author-email: urain39@qq.com
License: MIT
Keywords: cache,lru,plru,pseudo-lru
Platform: all
Classifier: Development Status :: 4 - Beta
Classifier: Operating System :: OS Independent
Classifier: Intended Audience :: Developers
Classifier: License :: OSI Approved :: BSD License
Classifier: Programming Language :: Python
Classifier: Programming Language :: Python :: Implementation
Classifier: Programming Language :: Python :: 3
Classifier: Programming Language :: Python :: 3.4
Classifier: Programming Language :: Python :: 3.5
Classifier: Programming Language :: Python :: 3.6
Classifier: Topic :: Software Development :: Libraries
License-File: LICENSE
